TOTY
